uw_file_processor_api/__init__.py
uw_file_processor_api/workflows/__init__.py
uw_file_processor_api/workflows/configs/__init__.py
uw_file_processor_api/workflows/configs/defines.py
uw_file_processor_api/workflows/configs/otel.py
uw_file_processor_api/workflows/controllers/__init__.py
uw_file_processor_api/workflows/controllers/iquine_controller.py
uw_file_processor_api/workflows/services/__init__.py
uw_file_processor_api/workflows/services/file_service.py
uw_file_processor_api/workflows/services/mapper_service.py
uw_file_processor_api/workflows/services/prediction_service.py
uw_file_processor_api/workflows/services/processor_service.py
uw_file_processor_api/workflows/services/training_service.py
uw_file_processor_api/workflows/steps/__init__.py
uw_file_processor_api/workflows/steps/download_from_s3.py
uw_file_processor_api/workflows/steps/process_file.py
uw_file_processor_api/workflows/utils/__init__.py
uw_file_processor_api/workflows/utils/dictionary.py
uw_file_processor_api/workflows/utils/strings.py
uw_file_processor_api-0.1.2.dist-info/METADATA
uw_file_processor_api-0.1.2.dist-info/WHEEL
uw_file_processor_api-0.1.2.dist-info/RECORD
