Metadata-Version: 2.1
Name: uw_file_processor_api
Version: 0.1.2
Summary: 
License: MIT
Author: Lucas Franca
Author-email: lucas@upowl.com.br
Requires-Python: >=3.9,<3.13
Classifier: License :: OSI Approved :: MIT License
Classifier: Programming Language :: Python :: 3
Classifier: Programming Language :: Python :: 3.9
Classifier: Programming Language :: Python :: 3.10
Classifier: Programming Language :: Python :: 3.11
Classifier: Programming Language :: Python :: 3.12
Requires-Dist: boto3 (>=1.28.68,<2.0.0)
Requires-Dist: confluent-kafka (>=2.3.0,<3.0.0)
Requires-Dist: flask (==2.3.3)
Requires-Dist: flask-restx (>=1.2.0,<2.0.0)
Requires-Dist: jupyter (>=1.0.0,<2.0.0)
Requires-Dist: matplotlib (>=3.8.2,<4.0.0)
Requires-Dist: notebook (>=7.0.6,<8.0.0)
Requires-Dist: openpyxl (>=3.1.2,<4.0.0)
Requires-Dist: pandas (>=2.1.1,<3.0.0)
Requires-Dist: pyarrow (>=14.0.1,<15.0.0)
Requires-Dist: pymongo (>=4.6.1,<5.0.0)
Requires-Dist: pytest (>=7.4.3,<8.0.0)
Requires-Dist: scikit-learn (>=1.3.2,<2.0.0)
Requires-Dist: statsmodels (>=0.14.0,<0.15.0)
